bangladeshi_parcel_tracker/__init__.py
bangladeshi_parcel_tracker/base.py
bangladeshi_parcel_tracker/cli.py
bangladeshi_parcel_tracker/providers/__init__.py
bangladeshi_parcel_tracker/providers/pathao.py
bangladeshi_parcel_tracker/providers/redx.py
bangladeshi_parcel_tracker/providers/rokomari.py
bangladeshi_parcel_tracker/providers/steadfast.py
bangladeshi_parcel_tracker/providers/sundarban.py
bangladeshi_parcel_tracker-1.3.0.dist-info/licenses/LICENSE
bangladeshi_parcel_tracker-1.3.0.dist-info/METADATA
bangladeshi_parcel_tracker-1.3.0.dist-info/WHEEL
bangladeshi_parcel_tracker-1.3.0.dist-info/entry_points.txt
bangladeshi_parcel_tracker-1.3.0.dist-info/top_level.txt
bangladeshi_parcel_tracker-1.3.0.dist-info/RECORD
