Metadata-Version: 2.4
Name: bangladeshi-parcel-tracker
Version: 1.3.0
Summary: A Python package for tracking parcels from Bangladeshi courier services
Home-page: https://github.com/mdminhazulhaque/bangladeshi-parcel-tracker
Author: Minhaz
Author-email: your.email@example.com
Project-URL: Bug Reports, https://github.com/mdminhazulhaque/bangladeshi-parcel-tracker/issues
Project-URL: Source, https://github.com/mdminhazulhaque/bangladeshi-parcel-tracker
Keywords: bangladesh parcel tracking courier redx steadfast pathao rokomari
Classifier: Development Status :: 3 - Alpha
Classifier: Intended Audience :: Developers
Classifier: License :: OSI Approved :: MIT License
Classifier: Operating System :: OS Independent
Classifier: Programming Language :: Python :: 3
Classifier: Programming Language :: Python :: 3.8
Classifier: Programming Language :: Python :: 3.9
Classifier: Programming Language :: Python :: 3.10
Classifier: Programming Language :: Python :: 3.11
Classifier: Programming Language :: Python :: 3.12
Requires-Python: >=3.8
License-File: LICENSE
Requires-Dist: requests>=2.25.0
Requires-Dist: click>=8.0.0
Requires-Dist: tabulate>=0.8.0
Dynamic: author
Dynamic: author-email
Dynamic: classifier
Dynamic: description
Dynamic: description-content-type
Dynamic: home-page
Dynamic: keywords
Dynamic: license-file
Dynamic: project-url
Dynamic: requires-dist
Dynamic: requires-python
Dynamic: summary
